{
  "kind": "collectionType",
  "collectionName": "logo_bg_photos",
  "info": {
    "singularName": "logo-bg-photo",
    "pluralName": "logo-bg-photos",
    "displayName": "PressKit/Logo-Bg-Photo",
    "description": ""
  },
  "options": {
    "draftAndPublish": true
  },
  "pluginOptions": {},
  "attributes": {
    "photo": {
      "allowedTypes": [
        "images"
      ],
      "type": "media",
      "multiple": false,
      "required": true
    },
    "logoColor": {
      "type": "enumeration",
      "enum": [
        "white",
        "black",
        "grey"
      ],
      "required": true,
      "default": "white"
    },
    "state": {
      "type": "enumeration",
      "enum": [
        "yes",
        "no",
        "alert"
      ],
      "required": true,
      "default": "yes"
    },
    "sortWeight": {
      "type": "integer",
      "required": true,
      "min": 0,
      "default": 0
    },
    "active": {
      "type": "boolean",
      "required": true
    }
  }
}
