{
  "kind": "collectionType",
  "collectionName": "sections",
  "info": {
    "singularName": "section",
    "pluralName": "sections",
    "displayName": "Menu/Sections",
    "description": ""
  },
  "options": {
    "draftAndPublish": true
  },
  "pluginOptions": {
    "i18n": {
      "localized": true
    }
  },
  "attributes": {
    "code": {
      "pluginOptions": {
        "i18n": {
          "localized": false
        }
      },
      "type": "string",
      "required": true
    },
    "title": {
      "pluginOptions": {
        "i18n": {
          "localized": true
        }
      },
      "type": "string",
      "required": true
    },
    "description": {
      "pluginOptions": {
        "i18n": {
          "localized": true
        }
      },
      "type": "string",
      "required": false
    },
    "icon": {
      "type": "media",
      "multiple": false,
      "required": false,
      "allowedTypes": [
        "images"
      ],
      "pluginOptions": {
        "i18n": {
          "localized": false
        }
      }
    },
    "link": {
      "pluginOptions": {
        "i18n": {
          "localized": false
        }
      },
      "type": "string",
      "required": true
    },
    "isExternal": {
      "pluginOptions": {
        "i18n": {
          "localized": false
        }
      },
      "type": "boolean",
      "default": false,
      "required": true
    },
    "sortWeight": {
      "pluginOptions": {
        "i18n": {
          "localized": false
        }
      },
      "type": "integer",
      "required": true,
      "min": 0,
      "default": 0
    },
    "active": {
      "pluginOptions": {
        "i18n": {
          "localized": false
        }
      },
      "type": "boolean",
      "required": true
    },
    "chapter": {
      "type": "relation",
      "relation": "oneToOne",
      "target": "api::chapter.chapter"
    }
  }
}
